methtimer/__init__.py
methtimer-0.0.1.dist-info/METADATA
methtimer-0.0.1.dist-info/RECORD
methtimer-0.0.1.dist-info/WHEEL
methtimer-0.0.1.dist-info/top_level.txt
