Metadata-Version: 2.1
Name: methtimer
Version: 0.0.1
Summary: UNKNOWN
Home-page: https://gitlab.com/AbiramK/methtimer
Author: AbiramK
Author-email: abiramkannan99@outlook.com
License: UNKNOWN
Platform: UNKNOWN
Classifier: Programming Language :: Python :: 3
Classifier: License :: OSI Approved :: GNU General Public License (GPL)
Classifier: Operating System :: OS Independent
